cmplib/__init__.py
cmplib-1.3.0.dist-info/LICENSE
cmplib-1.3.0.dist-info/LICENSE-GPL-3.0
cmplib-1.3.0.dist-info/METADATA
cmplib-1.3.0.dist-info/WHEEL
cmplib-1.3.0.dist-info/RECORD
