Metadata-Version: 2.1
Name: cmplib
Version: 1.3.0
Summary: Library for writing composable predicates
Home-page: https://git.goral.net.pl/cmplib.git/about
License: LGPL-3.0-only
Author: Michal Goral
Author-email: dev@goral.net.pl
Requires-Python: >=3.8,<4.0
Classifier: Development Status :: 5 - Production/Stable
Classifier: Intended Audience :: Developers
Classifier: License :: OSI Approved :: GNU Lesser General Public License v3 (LGPLv3)
Classifier: Programming Language :: Python :: 3
Classifier: Programming Language :: Python :: 3.8
Classifier: Programming Language :: Python :: 3.9
Classifier: Programming Language :: Python :: 3.10
Classifier: Programming Language :: Python :: 3.11
Classifier: Programming Language :: Python :: 3.12
Project-URL: Documentation, https://git.goral.net.pl/cmplib.git/about
Project-URL: Repository, https://git.goral.net.pl/cmplib.git
